{"nodes": [{"id": "hulu_documentation_executive_dashboard", "label": "Hulu Executive Dashboard Feature", "file_type": "concept", "source_file": "hulu-documentation.html", "source_location": null, "source_url": null, "captured_at": null, "author": null, "contributor": null}, {"id": "hulu_documentation_inbox_capture_desk", "label": "Hulu Inbox Capture Desk Feature", "file_type": "concept", "source_file": "hulu-documentation.html", "source_location": null, "source_url": null, "captured_at": null, "author": null, "contributor": null}, {"id": "hulu_documentation_projects_and_tasks", "label": "Hulu Projects & Tasks Feature", "file_type": "concept", "source_file": "hulu-documentation.html", "source_location": null, "source_url": null, "captured_at": null, "author": null, "contributor": null}, {"id": "hulu_documentation_habits_consistency", "label": "Hulu Habits Consistency Feature", "file_type": "concept", "source_file": "hulu-documentation.html", "source_location": null, "source_url": null, "captured_at": null, "author": null, "contributor": null}, {"id": "hulu_documentation_journal_reflections", "label": "Hulu Journal Reflections Feature", "file_type": "concept", "source_file": "hulu-documentation.html", "source_location": null, "source_url": null, "captured_at": null, "author": null, "contributor": null}, {"id": "hulu_documentation_academy_library_and_srs", "label": "Hulu Academy Library and SRS Feature", "file_type": "concept", "source_file": "hulu-documentation.html", "source_location": null, "source_url": null, "captured_at": null, "author": null, "contributor": null}, {"id": "hulu_documentation_ai_research_agent", "label": "Hulu AI Research Agent Feature", "file_type": "concept", "source_file": "hulu-documentation.html", "source_location": null, "source_url": null, "captured_at": null, "author": null, "contributor": null}, {"id": "hulu_documentation_ask_oracle_chat", "label": "Hulu Ask Oracle Chat Feature", "file_type": "concept", "source_file": "hulu-documentation.html", "source_location": null, "source_url": null, "captured_at": null, "author": null, "contributor": null}, {"id": "hulu_documentation_review_room_checkpoints", "label": "Hulu Review Room Checkpoints Feature", "file_type": "concept", "source_file": "hulu-documentation.html", "source_location": null, "source_url": null, "captured_at": null, "author": null, "contributor": null}, {"id": "hulu_documentation_focus_pomodoro", "label": "Hulu Focus Pomodoro Feature", "file_type": "concept", "source_file": "hulu-documentation.html", "source_location": null, "source_url": null, "captured_at": null, "author": null, "contributor": null}, {"id": "hulu_documentation_soul_blueprint_engine", "label": "Hulu Soul Blueprint Engine", "file_type": "concept", "source_file": "hulu-documentation.html", "source_location": null, "source_url": null, "captured_at": null, "author": null, "contributor": null}, {"id": "hulu_documentation_relational_database", "label": "Hulu Relational Database Setup", "file_type": "concept", "source_file": "hulu-documentation.html", "source_location": null, "source_url": null, "captured_at": null, "author": null, "contributor": null}, {"id": "hulu_documentation_rls_security", "label": "Hulu RLS Security Policies", "file_type": "concept", "source_file": "hulu-documentation.html", "source_location": null, "source_url": null, "captured_at": null, "author": null, "contributor": null}, {"id": "hulu_documentation_api_capture_enrich", "label": "Hulu API Capture Enrich Endpoint", "file_type": "code", "source_file": "hulu-documentation.html", "source_location": null, "source_url": null, "captured_at": null, "author": null, "contributor": null}, {"id": "hulu_documentation_api_intelligence_digest", "label": "Hulu API Intelligence Digest Endpoint", "file_type": "code", "source_file": "hulu-documentation.html", "source_location": null, "source_url": null, "captured_at": null, "author": null, "contributor": null}, {"id": "hulu_documentation_api_oracle_chat", "label": "Hulu API Oracle Chat Endpoint", "file_type": "code", "source_file": "hulu-documentation.html", "source_location": null, "source_url": null, "captured_at": null, "author": null, "contributor": null}, {"id": "hulu_documentation_api_research_search", "label": "Hulu API Research Search Endpoint", "file_type": "code", "source_file": "hulu-documentation.html", "source_location": null, "source_url": null, "captured_at": null, "author": null, "contributor": null}, {"id": "hulu_documentation_api_research_outline", "label": "Hulu API Research Outline Endpoint", "file_type": "code", "source_file": "hulu-documentation.html", "source_location": null, "source_url": null, "captured_at": null, "author": null, "contributor": null}, {"id": "hulu_documentation_api_research_generate_module", "label": "Hulu API Research Generate Module Endpoint", "file_type": "code", "source_file": "hulu-documentation.html", "source_location": null, "source_url": null, "captured_at": null, "author": null, "contributor": null}], "edges": [{"source": "hulu_documentation_inbox_capture_desk", "target": "hulu_documentation_api_capture_enrich", "relation": "references", "confidence": "EXTRACTED", "confidence_score": 1.0, "source_file": "hulu-documentation.html", "source_location": null, "weight": 1.0}, {"source": "hulu_documentation_ask_oracle_chat", "target": "hulu_documentation_api_oracle_chat", "relation": "references", "confidence": "EXTRACTED", "confidence_score": 1.0, "source_file": "hulu-documentation.html", "source_location": null, "weight": 1.0}, {"source": "hulu_documentation_ai_research_agent", "target": "hulu_documentation_api_research_search", "relation": "references", "confidence": "EXTRACTED", "confidence_score": 1.0, "source_file": "hulu-documentation.html", "source_location": null, "weight": 1.0}, {"source": "hulu_documentation_ai_research_agent", "target": "hulu_documentation_api_research_outline", "relation": "references", "confidence": "EXTRACTED", "confidence_score": 1.0, "source_file": "hulu-documentation.html", "source_location": null, "weight": 1.0}, {"source": "hulu_documentation_ai_research_agent", "target": "hulu_documentation_api_research_generate_module", "relation": "references", "confidence": "EXTRACTED", "confidence_score": 1.0, "source_file": "hulu-documentation.html", "source_location": null, "weight": 1.0}, {"source": "hulu_documentation_executive_dashboard", "target": "design_heritage_design_system", "relation": "references", "confidence": "INFERRED", "confidence_score": 0.85, "source_file": "hulu-documentation.html", "source_location": null, "weight": 1.0}, {"source": "hulu_documentation_inbox_capture_desk", "target": "design_heritage_design_system", "relation": "references", "confidence": "INFERRED", "confidence_score": 0.85, "source_file": "hulu-documentation.html", "source_location": null, "weight": 1.0}, {"source": "hulu_documentation_projects_and_tasks", "target": "design_heritage_design_system", "relation": "references", "confidence": "INFERRED", "confidence_score": 0.85, "source_file": "hulu-documentation.html", "source_location": null, "weight": 1.0}, {"source": "hulu_documentation_soul_blueprint_engine", "target": "hulu_documentation_relational_database", "relation": "shares_data_with", "confidence": "INFERRED", "confidence_score": 0.95, "source_file": "hulu-documentation.html", "source_location": null, "weight": 1.0}, {"source": "hulu_documentation_relational_database", "target": "hulu_documentation_rls_security", "relation": "references", "confidence": "EXTRACTED", "confidence_score": 1.0, "source_file": "hulu-documentation.html", "source_location": null, "weight": 1.0}], "hyperedges": [{"id": "hulu_os_feature_suite", "label": "Hulu OS Feature Suite", "nodes": ["hulu_documentation_executive_dashboard", "hulu_documentation_inbox_capture_desk", "hulu_documentation_projects_and_tasks", "hulu_documentation_habits_consistency", "hulu_documentation_journal_reflections", "hulu_documentation_academy_library_and_srs", "hulu_documentation_ai_research_agent", "hulu_documentation_ask_oracle_chat", "hulu_documentation_review_room_checkpoints", "hulu_documentation_focus_pomodoro"], "relation": "form", "confidence": "EXTRACTED", "confidence_score": 1.0, "source_file": "hulu-documentation.html"}]}